otis/__init__.py
otis/finger_motor.py
otis/kinematics.py
otis/otis.py
reachy_otis-1.0.1.dist-info/LICENSE
reachy_otis-1.0.1.dist-info/METADATA
reachy_otis-1.0.1.dist-info/WHEEL
reachy_otis-1.0.1.dist-info/top_level.txt
reachy_otis-1.0.1.dist-info/RECORD
