Metadata-Version: 2.1
Name: reachy-otis
Version: 1.0.1
Summary: Otis: handwriting end-effector for Reachy.
Home-page: https://github.com/pollen-robotics/otis
Author: Pollen Robotics
Author-email: contact@pollen-robotics.com
License: UNKNOWN
Platform: UNKNOWN
Requires-Dist: numpy
Requires-Dist: reachy (>=1.3)
Requires-Dist: matplotlib
